tpall/__init__.py
tpall/af.py
tpall/re.py
tpall-0.3.dist-info/METADATA
tpall-0.3.dist-info/WHEEL
tpall-0.3.dist-info/licenses/LICENSE
tpall-0.3.dist-info/RECORD
