Metadata-Version: 2.3
Name: tpall
Version: 0.3
Summary: Quelques classes pour le TP de l'UE Automates, Langages et Logique
Project-URL: Homepage, https://github.com/nopid/tpall
Project-URL: Issues, https://github.com/nopid/tpall/issues
Author-email: Nicolas Ollinger <nopid@free.fr>
License-File: LICENSE
Classifier: Intended Audience :: Developers
Classifier: License :: OSI Approved :: CEA CNRS Inria Logiciel Libre License, version 2.1 (CeCILL-2.1)
Classifier: Programming Language :: Python :: 3
Requires-Python: >=3.10
Requires-Dist: graphviz
Requires-Dist: svgling
